<archimate:ArchimateDiagramModel
    xmlns:xsi="http://www.w3.org/2001/XMLSchema-instance"
    xmlns:archimate="http://www.archimatetool.com/archimate"
    name="C - Drivefase Steg 1 (kjøp og salg)"
    id="9d4e1521-4584-481b-89ed-d509b5291fd3">
  <children
      xsi:type="archimate:DiagramModelArchimateObject"
      id="1ce1b28d-d5e8-4eb8-921c-b189a704ded5"
      font="1|Lucida Grande|12.0|0|COCOA|1|"
      fontColor="#000000"
      lineColor="#5c5c5c"
      fillColor="#ffffb5">
    <bounds
        x="81"
        y="142"
        width="152"
        height="56"/>
    <archimateElement
        xsi:type="archimate:BusinessService"
        href="BusinessService_id-05a03773-8827-4159-88f0-6cc1d4e3d496.xml#id-05a03773-8827-4159-88f0-6cc1d4e3d496"/>
  </children>
  <children
      xsi:type="archimate:DiagramModelArchimateObject"
      id="983badf4-7a9d-435a-ba04-404f7802eb62"
      font="1|Lucida Grande|12.0|0|COCOA|1|"
      fontColor="#000000"
      lineColor="#5c5c5c"
      fillColor="#ffffb5">
    <bounds
        x="81"
        y="312"
        width="152"
        height="30"/>
    <archimateElement
        xsi:type="archimate:BusinessService"
        href="BusinessService_id-c909ca84-28ac-4934-beab-53abbfd748fc.xml#id-c909ca84-28ac-4934-beab-53abbfd748fc"/>
  </children>
  <children
      xsi:type="archimate:DiagramModelArchimateObject"
      id="53720a30-b373-4002-b132-f12d4d7fd37d"
      font="1|Lucida Grande|12.0|0|COCOA|1|"
      fontColor="#000000"
      lineColor="#5c5c5c"
      fillColor="#ffffb5">
    <bounds
        x="72"
        y="-10"
        width="445"
        height="55"/>
    <archimateElement
        xsi:type="archimate:BusinessProcess"
        href="BusinessProcess_id-853791ec-4bd5-43f5-9a7a-6197e1851d8d.xml#id-853791ec-4bd5-43f5-9a7a-6197e1851d8d"/>
  </children>
  <children
      xsi:type="archimate:DiagramModelArchimateObject"
      id="74317aa6-20fc-412c-8a85-e718f631a6a0"
      font="1|Lucida Grande|12.0|0|COCOA|1|"
      fontColor="#000000"
      lineColor="#5c5c5c"
      fillColor="#ffffb5">
    <bounds
        x="78"
        y="56"
        width="157"
        height="55"/>
    <archimateElement
        xsi:type="archimate:BusinessProcess"
        href="BusinessProcess_id-85fa73e0-1eee-44f4-a782-6141b154f8ab.xml#id-85fa73e0-1eee-44f4-a782-6141b154f8ab"/>
  </children>
  <children
      xsi:type="archimate:DiagramModelArchimateObject"
      id="53134edd-9ccf-4787-8114-a663b6d4b37b"
      font="1|Lucida Grande|12.0|0|COCOA|1|"
      fontColor="#000000"
      lineColor="#5c5c5c"
      fillColor="#ffffb5">
    <bounds
        x="81"
        y="257"
        width="152"
        height="41"/>
    <archimateElement
        xsi:type="archimate:BusinessService"
        href="BusinessService_id-886adc1d-f0ed-41b4-ae3a-dc191b9c8eb8.xml#id-886adc1d-f0ed-41b4-ae3a-dc191b9c8eb8"/>
  </children>
  <children
      xsi:type="archimate:DiagramModelArchimateObject"
      id="ad6249e1-a718-4e2f-bc98-4fd16903059f"
      font="1|Lucida Grande|12.0|0|COCOA|1|"
      fontColor="#000000"
      lineColor="#5c5c5c"
      fillColor="#ffffb5">
    <bounds
        x="81"
        y="210"
        width="152"
        height="31"/>
    <archimateElement
        xsi:type="archimate:BusinessService"
        href="BusinessService_id-8b9bd5e8-97f7-4a9a-b8c1-e663adf8bf04.xml#id-8b9bd5e8-97f7-4a9a-b8c1-e663adf8bf04"/>
  </children>
  <children
      xsi:type="archimate:DiagramModelNote"
      id="c6e4d186-b873-4028-84e6-6fc9940daad1"
      font="1|Lucida Grande|12.0|0|COCOA|1|"
      fontColor="#000000"
      lineColor="#5c5c5c"
      textAlignment="1"
      fillColor="#ffffff"
      content="STEG">
    <bounds
        x="-72"
        y="-10"
        width="132"
        height="144"/>
  </children>
  <children
      xsi:type="archimate:DiagramModelNote"
      id="d6911fce-63cf-4b79-bc06-2eef19afe41c"
      font="1|Lucida Grande|12.0|0|COCOA|1|"
      fontColor="#000000"
      lineColor="#5c5c5c"
      textAlignment="1"
      fillColor="#ffffff"
      content="AKTIVITETER">
    <bounds
        x="-72"
        y="141"
        width="132"
        height="384"/>
  </children>
  <children
      xsi:type="archimate:DiagramModelNote"
      id="40ad6900-9577-4731-a959-b400d0dadea7"
      font="1|Lucida Grande|12.0|0|COCOA|1|"
      fontColor="#000000"
      lineColor="#5c5c5c"
      textAlignment="1"
      fillColor="#ffffff"
      content="TILTAK">
    <bounds
        x="-72"
        y="539"
        width="132"
        height="384"/>
  </children>
</archimate:ArchimateDiagramModel>
